pixlise_client/__init__.py
pixlise_client/pixlise-linux-amd64.h
pixlise_client/pixlise-linux-amd64.so
pixlise_client/pixlise-windows-amd64.dll
pixlise_client/pixlise-windows-amd64.h
pixlise_client/pixlise.py
pixlise_client/pixlisemsgs/__init__.py
pixlise_client/pixlisemsgs/__init__.pyi
pixlise_client/pixlisemsgs/detector_config_msgs_pb2.py
pixlise_client/pixlisemsgs/detector_config_pb2.py
pixlise_client/pixlisemsgs/diffraction_data_pb2.py
pixlise_client/pixlisemsgs/diffraction_detected_peak_msgs_pb2.py
pixlise_client/pixlisemsgs/diffraction_manual_msgs_pb2.py
pixlise_client/pixlisemsgs/diffraction_status_msgs_pb2.py
pixlise_client/pixlisemsgs/doi_msgs_pb2.py
pixlise_client/pixlisemsgs/doi_pb2.py
pixlise_client/pixlisemsgs/element_set_msgs_pb2.py
pixlise_client/pixlisemsgs/element_set_pb2.py
pixlise_client/pixlisemsgs/export_msgs_pb2.py
pixlise_client/pixlisemsgs/export_pb2.py
pixlise_client/pixlisemsgs/expression_group_msgs_pb2.py
pixlise_client/pixlisemsgs/expression_group_pb2.py
pixlise_client/pixlisemsgs/expression_msgs_pb2.py
pixlise_client/pixlisemsgs/expressions_pb2.py
pixlise_client/pixlisemsgs/image_beam_location_msgs_pb2.py
pixlise_client/pixlisemsgs/image_beam_location_pb2.py
pixlise_client/pixlisemsgs/image_coreg_msgs_pb2.py
pixlise_client/pixlisemsgs/image_coreg_pb2.py
pixlise_client/pixlisemsgs/image_msgs_pb2.py
pixlise_client/pixlisemsgs/image_pb2.py
pixlise_client/pixlisemsgs/job_msgs_pb2.py
pixlise_client/pixlisemsgs/job_pb2.py
pixlise_client/pixlisemsgs/log_msgs_pb2.py
pixlise_client/pixlisemsgs/log_pb2.py
pixlise_client/pixlisemsgs/memoisation_msgs_pb2.py
pixlise_client/pixlisemsgs/memoisation_pb2.py
pixlise_client/pixlisemsgs/module_msgs_pb2.py
pixlise_client/pixlisemsgs/modules_pb2.py
pixlise_client/pixlisemsgs/notification_msgs_pb2.py
pixlise_client/pixlisemsgs/notification_pb2.py
pixlise_client/pixlisemsgs/ownership_access_msgs_pb2.py
pixlise_client/pixlisemsgs/ownership_access_pb2.py
pixlise_client/pixlisemsgs/permissions_pb2.py
pixlise_client-0.0.26.dist-info/METADATA
pixlise_client-0.0.26.dist-info/WHEEL
pixlise_client-0.0.26.dist-info/licenses/LICENSE
pixlise_client-0.0.26.dist-info/RECORD
